thecurator/__init__.py
thecurator/table_description_schema.yml
thecurator/private/__init__.py
thecurator/private/table_description.py
thecurator-0.2.1.dist-info/DESCRIPTION.rst
thecurator-0.2.1.dist-info/METADATA
thecurator-0.2.1.dist-info/RECORD
thecurator-0.2.1.dist-info/WHEEL
thecurator-0.2.1.dist-info/metadata.json
thecurator-0.2.1.dist-info/top_level.txt
