Metadata-Version: 2.0
Name: thecurator
Version: 0.2.1
Summary: UNKNOWN
Home-page: https://github.com/fny/thecurator
Author: Faraz Yashar
Author-email: faraz.yashar@gmail.com
License: MIT
Platform: UNKNOWN
Classifier: Intended Audience :: Developers
Classifier: Topic :: Software Development
Classifier: Topic :: Utilities
Classifier: Programming Language :: Python :: 3
Requires-Dist: jsonschema
Requires-Dist: pyaml
Requires-Dist: sqlalchemy
Provides-Extra: dev
Requires-Dist: dateparser; extra == 'dev'
Requires-Dist: pandas; extra == 'dev'
Requires-Dist: pytest; extra == 'dev'
